{"HN-YO":{"countryCode":"HN","code":"HN-YO","name":"Yoro","fips":"HO18","wikiDataId":"Q153814"},"HN-VA":{"countryCode":"HN","code":"HN-VA","name":"Valle","fips":"HO17","wikiDataId":"Q867097"},"HN-SB":{"countryCode":"HN","code":"HN-SB","name":"Santa Bárbara","fips":"HO16","wikiDataId":"Q108106"},"HN-OL":{"countryCode":"HN","code":"HN-OL","name":"Olancho","fips":"HO15","wikiDataId":"Q83631271"},"HN-OC":{"countryCode":"HN","code":"HN-OC","name":"Ocotepeque","fips":"HO14","wikiDataId":"Q2182554"},"HN-LE":{"countryCode":"HN","code":"HN-LE","name":"Lempira","fips":"HO13","wikiDataId":"Q744138"},"HN-LP":{"countryCode":"HN","code":"HN-LP","name":"La Paz","fips":"HO12","wikiDataId":"Q58759"},"HN-IB":{"countryCode":"HN","code":"HN-IB","name":"Islas de la Bahía","fips":"HO11","wikiDataId":"Q3593570"},"HN-IN":{"countryCode":"HN","code":"HN-IN","name":"Intibucá","fips":"HO10","wikiDataId":"Q2395884"},"HN-GD":{"countryCode":"HN","code":"HN-GD","name":"Gracias a Dios","fips":"HO09","wikiDataId":"Q738084"},"HN-FM":{"countryCode":"HN","code":"HN-FM","name":"Francisco Morazán","fips":"HO08","wikiDataId":"Q332111"},"HN-EP":{"countryCode":"HN","code":"HN-EP","name":"El Paraíso","fips":"HO07","wikiDataId":"Q111730822"},"HN-CR":{"countryCode":"HN","code":"HN-CR","name":"Cortés","fips":"HO06","wikiDataId":"Q767244"},"HN-CP":{"countryCode":"HN","code":"HN-CP","name":"Copán","fips":"HO05","wikiDataId":"Q843984"},"HN-CM":{"countryCode":"HN","code":"HN-CM","name":"Comayagua","fips":"HO04","wikiDataId":"Q6088785"},"HN-CL":{"countryCode":"HN","code":"HN-CL","name":"Colón","fips":"HO03","wikiDataId":"Q820514"},"HN-CH":{"countryCode":"HN","code":"HN-CH","name":"Choluteca","fips":"HO02","wikiDataId":"Q1773148"},"HN-AT":{"countryCode":"HN","code":"HN-AT","name":"Atlántida","fips":"HO01","wikiDataId":"Q1549798"}}